priority_manager/__init__.py
priority_manager/config.yaml
priority_manager/main.py
priority_manager/commands/__init__.py
priority_manager/commands/add.py
priority_manager/commands/archive.py
priority_manager/commands/conf.py
priority_manager/commands/edit.py
priority_manager/commands/export.py
priority_manager/commands/gantt.py
priority_manager/commands/ls.py
priority_manager/commands/search_filter.py
priority_manager/tests/__init__.py
priority_manager/tests/conftest.py
priority_manager/tests/test_add.py
priority_manager/tests/test_edit.py
priority_manager/tests/test_export.py
priority_manager/tests/test_ls.py
priority_manager/utils/__init__.py
priority_manager/utils/config.py
priority_manager/utils/helpers.py
priority_manager/utils/logger.py
priority_manager-0.1.25.dist-info/METADATA
priority_manager-0.1.25.dist-info/WHEEL
priority_manager-0.1.25.dist-info/entry_points.txt
priority_manager-0.1.25.dist-info/top_level.txt
priority_manager-0.1.25.dist-info/RECORD
