Metadata-Version: 2.1
Name: priority_manager
Version: 0.1.25
Summary: A CLI tool for managing tasks with priorities and statuses.
Home-page: https://github.com/DavidTbilisi/PriorityManager
Author: David Chincharashvili
Author-email: davidchincharashvili@gmail.com
Classifier: Programming Language :: Python :: 3
Classifier: License :: OSI Approved :: MIT License
Classifier: Operating System :: OS Independent
Requires-Python: >=3.7
Requires-Dist: click==8.1.7
Requires-Dist: iniconfig==2.0.0
Requires-Dist: markdown-it-py==3.0.0
Requires-Dist: mdurl==0.1.2
Requires-Dist: packaging==24.2
Requires-Dist: plotly==5.24.1
Requires-Dist: pluggy==1.5.0
Requires-Dist: Pygments==2.18.0
Requires-Dist: pytest==8.3.4
Requires-Dist: PyYAML==6.0.2
Requires-Dist: rich==13.9.4
Requires-Dist: setuptools==75.6.0
Requires-Dist: shellingham==1.5.4
Requires-Dist: tabulate==0.9.0
Requires-Dist: tenacity==9.0.0
Requires-Dist: typing_extensions==4.12.2
